{
  "uiSchemaVersion": 2,
  "fixtureId": "id1000003561514184",
  "startTime": "2026-05-08T18:30:00.000Z",
  "day": "2026-05-08",
  "tournamentId": 35,
  "tournamentName": "Bundesliga",
  "categoryName": "Germany",
  "home": "Borussia Dortmund",
  "away": "Eintracht Frankfurt",
  "bookmakerKey": "superbet.ro",
  "fixturePath": "https://superbet.com/offer-event/e-12025298",
  "featuredMarkets": {
    "ft1x2": null,
    "btts": {
      "key": "btts",
      "label": "BTTS",
      "marketId": "104",
      "bookmakerMarketId": "066f33bb-75c7-5f6d-99e1-218708369539",
      "outcomes": [
        {
          "key": "YES",
          "label": "Yes",
          "outcomeId": "104",
          "price": 1.49,
          "changedAt": "2026-04-27T17:54:55.682Z"
        },
        {
          "key": "NO",
          "label": "No",
          "outcomeId": "105",
          "price": 2.5,
          "changedAt": "2026-04-27T17:54:55.682Z"
        }
      ]
    },
    "doubleChance": null
  },
  "selectionIndex": {
    "BTTS|YES": {
      "market": "BTTS",
      "selection": "YES",
      "label": "BTTS YES",
      "marketId": "104",
      "outcomeId": "104",
      "bookmakerMarketId": "066f33bb-75c7-5f6d-99e1-218708369539",
      "price": 1.49,
      "changedAt": "2026-04-27T17:54:55.682Z"
    },
    "BTTS|NO": {
      "market": "BTTS",
      "selection": "NO",
      "label": "BTTS NO",
      "marketId": "104",
      "outcomeId": "105",
      "bookmakerMarketId": "066f33bb-75c7-5f6d-99e1-218708369539",
      "price": 2.5,
      "changedAt": "2026-04-27T17:54:55.682Z"
    },
    "Double Chance|1X": {
      "market": "Double Chance",
      "selection": "1X",
      "label": "Double Chance 1X",
      "marketId": "101902",
      "outcomeId": "101902",
      "bookmakerMarketId": null,
      "price": null,
      "changedAt": null
    },
    "Double Chance|12": {
      "market": "Double Chance",
      "selection": "12",
      "label": "Double Chance 12",
      "marketId": "101902",
      "outcomeId": "101903",
      "bookmakerMarketId": null,
      "price": null,
      "changedAt": null
    },
    "Double Chance|X2": {
      "market": "Double Chance",
      "selection": "X2",
      "label": "Double Chance X2",
      "marketId": "101902",
      "outcomeId": "101904",
      "bookmakerMarketId": null,
      "price": null,
      "changedAt": null
    },
    "Goals 1.5|OVER": {
      "market": "Goals 1.5",
      "selection": "OVER",
      "label": "Goals 1.5 OVER",
      "marketId": "108",
      "outcomeId": "108",
      "bookmakerMarketId": "999d2b92-1c0b-5f43-9fa0-8bcf6360552d",
      "price": 1.11,
      "changedAt": "2026-04-26T22:37:52.679Z"
    },
    "Goals 1.5|UNDER": {
      "market": "Goals 1.5",
      "selection": "UNDER",
      "label": "Goals 1.5 UNDER",
      "marketId": "108",
      "outcomeId": "109",
      "bookmakerMarketId": "999d2b92-1c0b-5f43-9fa0-8bcf6360552d",
      "price": 6.7,
      "changedAt": "2026-04-27T17:54:55.682Z"
    },
    "Goals 2.5|OVER": {
      "market": "Goals 2.5",
      "selection": "OVER",
      "label": "Goals 2.5 OVER",
      "marketId": "1010",
      "outcomeId": "1010",
      "bookmakerMarketId": "8a861e27-268d-5ba1-ae35-d4c537673635",
      "price": 1.39,
      "changedAt": "2026-04-26T22:37:52.679Z"
    },
    "Goals 2.5|UNDER": {
      "market": "Goals 2.5",
      "selection": "UNDER",
      "label": "Goals 2.5 UNDER",
      "marketId": "1010",
      "outcomeId": "1011",
      "bookmakerMarketId": "8a861e27-268d-5ba1-ae35-d4c537673635",
      "price": 3,
      "changedAt": "2026-04-26T22:37:52.679Z"
    },
    "Goals 3.5|OVER": {
      "market": "Goals 3.5",
      "selection": "OVER",
      "label": "Goals 3.5 OVER",
      "marketId": "1012",
      "outcomeId": "1012",
      "bookmakerMarketId": "f77d8203-f483-5f83-977a-ab7b0692251b",
      "price": 1.97,
      "changedAt": "2026-04-26T22:37:52.679Z"
    },
    "Goals 3.5|UNDER": {
      "market": "Goals 3.5",
      "selection": "UNDER",
      "label": "Goals 3.5 UNDER",
      "marketId": "1012",
      "outcomeId": "1013",
      "bookmakerMarketId": "f77d8203-f483-5f83-977a-ab7b0692251b",
      "price": 1.85,
      "changedAt": "2026-04-26T22:37:52.679Z"
    },
    "Goals 4.5|OVER": {
      "market": "Goals 4.5",
      "selection": "OVER",
      "label": "Goals 4.5 OVER",
      "marketId": "1014",
      "outcomeId": "1014",
      "bookmakerMarketId": "56123ca0-3f21-586e-a9fd-4816d516465c",
      "price": 3.15,
      "changedAt": "2026-04-26T22:37:52.679Z"
    },
    "Goals 4.5|UNDER": {
      "market": "Goals 4.5",
      "selection": "UNDER",
      "label": "Goals 4.5 UNDER",
      "marketId": "1014",
      "outcomeId": "1015",
      "bookmakerMarketId": "56123ca0-3f21-586e-a9fd-4816d516465c",
      "price": 1.36,
      "changedAt": "2026-04-26T22:37:52.679Z"
    },
    "Corners 8.5|OVER": {
      "market": "Corners 8.5",
      "selection": "OVER",
      "label": "Corners 8.5 OVER",
      "marketId": "10799",
      "outcomeId": "10799",
      "bookmakerMarketId": null,
      "price": null,
      "changedAt": null
    },
    "Corners 8.5|UNDER": {
      "market": "Corners 8.5",
      "selection": "UNDER",
      "label": "Corners 8.5 UNDER",
      "marketId": "10799",
      "outcomeId": "10800",
      "bookmakerMarketId": null,
      "price": null,
      "changedAt": null
    },
    "Corners 9.5|OVER": {
      "market": "Corners 9.5",
      "selection": "OVER",
      "label": "Corners 9.5 OVER",
      "marketId": "10803",
      "outcomeId": "10803",
      "bookmakerMarketId": null,
      "price": null,
      "changedAt": null
    },
    "Corners 9.5|UNDER": {
      "market": "Corners 9.5",
      "selection": "UNDER",
      "label": "Corners 9.5 UNDER",
      "marketId": "10803",
      "outcomeId": "10804",
      "bookmakerMarketId": null,
      "price": null,
      "changedAt": null
    },
    "Corners 10.5|OVER": {
      "market": "Corners 10.5",
      "selection": "OVER",
      "label": "Corners 10.5 OVER",
      "marketId": "10807",
      "outcomeId": "10807",
      "bookmakerMarketId": null,
      "price": null,
      "changedAt": null
    },
    "Corners 10.5|UNDER": {
      "market": "Corners 10.5",
      "selection": "UNDER",
      "label": "Corners 10.5 UNDER",
      "marketId": "10807",
      "outcomeId": "10808",
      "bookmakerMarketId": null,
      "price": null,
      "changedAt": null
    },
    "Cards 3.5|OVER": {
      "market": "Cards 3.5",
      "selection": "OVER",
      "label": "Cards 3.5 OVER",
      "marketId": "10926",
      "outcomeId": "10926",
      "bookmakerMarketId": null,
      "price": null,
      "changedAt": null
    },
    "Cards 3.5|UNDER": {
      "market": "Cards 3.5",
      "selection": "UNDER",
      "label": "Cards 3.5 UNDER",
      "marketId": "10926",
      "outcomeId": "10927",
      "bookmakerMarketId": null,
      "price": null,
      "changedAt": null
    },
    "Cards 4.5|OVER": {
      "market": "Cards 4.5",
      "selection": "OVER",
      "label": "Cards 4.5 OVER",
      "marketId": "10930",
      "outcomeId": "10930",
      "bookmakerMarketId": null,
      "price": null,
      "changedAt": null
    },
    "Cards 4.5|UNDER": {
      "market": "Cards 4.5",
      "selection": "UNDER",
      "label": "Cards 4.5 UNDER",
      "marketId": "10930",
      "outcomeId": "10931",
      "bookmakerMarketId": null,
      "price": null,
      "changedAt": null
    },
    "Cards 5.5|OVER": {
      "market": "Cards 5.5",
      "selection": "OVER",
      "label": "Cards 5.5 OVER",
      "marketId": "10934",
      "outcomeId": "10934",
      "bookmakerMarketId": null,
      "price": null,
      "changedAt": null
    },
    "Cards 5.5|UNDER": {
      "market": "Cards 5.5",
      "selection": "UNDER",
      "label": "Cards 5.5 UNDER",
      "marketId": "10934",
      "outcomeId": "10935",
      "bookmakerMarketId": null,
      "price": null,
      "changedAt": null
    }
  },
  "markets": [
    {
      "marketId": "104",
      "bookmakerMarketId": "066f33bb-75c7-5f6d-99e1-218708369539",
      "outcomes": [
        {
          "outcomeId": "104",
          "playerKey": "0",
          "playerName": null,
          "price": 1.49,
          "changedAt": "2026-04-27T17:54:55.682Z",
          "bookmakerOutcomeId": "3f5902da-a783-5079-8904-b76e0ca7ce87"
        },
        {
          "outcomeId": "105",
          "playerKey": "0",
          "playerName": null,
          "price": 2.5,
          "changedAt": "2026-04-27T17:54:55.682Z",
          "bookmakerOutcomeId": "037de0e6-e78f-5c02-8965-1459a9239453"
        }
      ]
    },
    {
      "marketId": "106",
      "bookmakerMarketId": "f20451cd-2fc9-5660-8827-3909447ec2f6",
      "outcomes": [
        {
          "outcomeId": "106",
          "playerKey": "0",
          "playerName": null,
          "price": 1.01,
          "changedAt": "2026-04-26T22:37:52.679Z",
          "bookmakerOutcomeId": "cace718d-eed9-5a14-a2e0-20861c1ba43f"
        },
        {
          "outcomeId": "107",
          "playerKey": "0",
          "playerName": null,
          "price": 23,
          "changedAt": "2026-04-27T17:54:55.682Z",
          "bookmakerOutcomeId": "8db6a92a-973f-560f-a483-aee0456a72f5"
        }
      ]
    },
    {
      "marketId": "108",
      "bookmakerMarketId": "999d2b92-1c0b-5f43-9fa0-8bcf6360552d",
      "outcomes": [
        {
          "outcomeId": "108",
          "playerKey": "0",
          "playerName": null,
          "price": 1.11,
          "changedAt": "2026-04-26T22:37:52.679Z",
          "bookmakerOutcomeId": "e1d8375b-1435-50a2-9870-b3b6ea937ff8"
        },
        {
          "outcomeId": "109",
          "playerKey": "0",
          "playerName": null,
          "price": 6.7,
          "changedAt": "2026-04-27T17:54:55.682Z",
          "bookmakerOutcomeId": "9b1729e7-e728-59c3-972a-d6eeaaaf19c0"
        }
      ]
    },
    {
      "marketId": "1010",
      "bookmakerMarketId": "8a861e27-268d-5ba1-ae35-d4c537673635",
      "outcomes": [
        {
          "outcomeId": "1010",
          "playerKey": "0",
          "playerName": null,
          "price": 1.39,
          "changedAt": "2026-04-26T22:37:52.679Z",
          "bookmakerOutcomeId": "cab0bb00-5481-5e33-8d0d-4f971ac5cc4d"
        },
        {
          "outcomeId": "1011",
          "playerKey": "0",
          "playerName": null,
          "price": 3,
          "changedAt": "2026-04-26T22:37:52.679Z",
          "bookmakerOutcomeId": "33e12b9d-402c-5fdd-9ba8-a94ee7e32147"
        }
      ]
    },
    {
      "marketId": "1012",
      "bookmakerMarketId": "f77d8203-f483-5f83-977a-ab7b0692251b",
      "outcomes": [
        {
          "outcomeId": "1013",
          "playerKey": "0",
          "playerName": null,
          "price": 1.85,
          "changedAt": "2026-04-26T22:37:52.679Z",
          "bookmakerOutcomeId": "ce65ce7a-0173-52d3-80b0-53dfcf96106e"
        },
        {
          "outcomeId": "1012",
          "playerKey": "0",
          "playerName": null,
          "price": 1.97,
          "changedAt": "2026-04-26T22:37:52.679Z",
          "bookmakerOutcomeId": "d343dd2a-305e-5096-8bc8-2ff581220c90"
        }
      ]
    },
    {
      "marketId": "1014",
      "bookmakerMarketId": "56123ca0-3f21-586e-a9fd-4816d516465c",
      "outcomes": [
        {
          "outcomeId": "1015",
          "playerKey": "0",
          "playerName": null,
          "price": 1.36,
          "changedAt": "2026-04-26T22:37:52.679Z",
          "bookmakerOutcomeId": "ef1725c6-904b-527a-9cf8-d9986a1308f1"
        },
        {
          "outcomeId": "1014",
          "playerKey": "0",
          "playerName": null,
          "price": 3.15,
          "changedAt": "2026-04-26T22:37:52.679Z",
          "bookmakerOutcomeId": "09c0ed60-f5f5-543a-96cb-b5c1accf2bfd"
        }
      ]
    },
    {
      "marketId": "1016",
      "bookmakerMarketId": "39910ccf-8ad7-5036-8a5e-028c4ca0dc83",
      "outcomes": [
        {
          "outcomeId": "1017",
          "playerKey": "0",
          "playerName": null,
          "price": 1.15,
          "changedAt": "2026-04-26T22:37:52.679Z",
          "bookmakerOutcomeId": "7c621f8a-7618-53d5-968b-35c448b793fb"
        },
        {
          "outcomeId": "1016",
          "playerKey": "0",
          "playerName": null,
          "price": 5.55,
          "changedAt": "2026-04-26T22:37:52.679Z",
          "bookmakerOutcomeId": "2dedbfad-d304-55f0-9900-e2e50f06cc7e"
        }
      ]
    },
    {
      "marketId": "1018",
      "bookmakerMarketId": "3b52fd22-875e-501f-9f2d-0c36219354dd",
      "outcomes": [
        {
          "outcomeId": "1019",
          "playerKey": "0",
          "playerName": null,
          "price": 1.06,
          "changedAt": "2026-04-26T22:37:52.679Z",
          "bookmakerOutcomeId": "c47f36c2-63ba-5dd4-bf79-feb609e28195"
        },
        {
          "outcomeId": "1018",
          "playerKey": "0",
          "playerName": null,
          "price": 10,
          "changedAt": "2026-04-26T22:37:52.679Z",
          "bookmakerOutcomeId": "cd79cb39-802c-5e63-b43f-da5dc89aac62"
        }
      ]
    },
    {
      "marketId": "1036",
      "bookmakerMarketId": "14c8cc11-c957-5e8b-8b96-d1959b0bf20c",
      "outcomes": [
        {
          "outcomeId": "1037",
          "playerKey": "0",
          "playerName": null,
          "price": 1.02,
          "changedAt": "2026-04-26T22:37:52.679Z",
          "bookmakerOutcomeId": "2b2fb582-fe16-53ba-8112-342b79ccb22e"
        },
        {
          "outcomeId": "1036",
          "playerKey": "0",
          "playerName": null,
          "price": 14,
          "changedAt": "2026-04-27T17:54:55.682Z",
          "bookmakerOutcomeId": "64d6230c-c912-5a5f-bdc4-cb1565da52b3"
        }
      ]
    },
    {
      "marketId": "1044",
      "bookmakerMarketId": "9a119afc-4f3b-5b3a-828f-29b667809b04",
      "outcomes": [
        {
          "outcomeId": "1045",
          "playerKey": "0",
          "playerName": null,
          "price": 1.08,
          "changedAt": "2026-04-27T17:54:55.682Z",
          "bookmakerOutcomeId": "a497ed17-d6ea-5e8f-91bf-10a8ca87203a"
        },
        {
          "outcomeId": "1044",
          "playerKey": "0",
          "playerName": null,
          "price": 6.8,
          "changedAt": "2026-04-27T17:54:55.682Z",
          "bookmakerOutcomeId": "ca5d043f-9758-5258-9d8c-998182182c17"
        }
      ]
    },
    {
      "marketId": "1052",
      "bookmakerMarketId": "397cf016-b352-50da-8b42-92ab3c2e2492",
      "outcomes": [
        {
          "outcomeId": "1053",
          "playerKey": "0",
          "playerName": null,
          "price": 1.25,
          "changedAt": "2026-04-27T17:54:55.682Z",
          "bookmakerOutcomeId": "9a68fd83-2234-50cc-833c-2329e926c103"
        },
        {
          "outcomeId": "1052",
          "playerKey": "0",
          "playerName": null,
          "price": 3.7,
          "changedAt": "2026-04-27T17:54:55.682Z",
          "bookmakerOutcomeId": "299c25c3-3d98-512e-a673-c5d26ef6f5bb"
        }
      ]
    },
    {
      "marketId": "1060",
      "bookmakerMarketId": "68df6fdb-d0a5-5a69-9dc4-5c85726ca9ba",
      "outcomes": [
        {
          "outcomeId": "1061",
          "playerKey": "0",
          "playerName": null,
          "price": 1.64,
          "changedAt": "2026-04-27T17:54:55.682Z",
          "bookmakerOutcomeId": "b64d505f-bdcf-58ba-857c-ffe91e383fb4"
        },
        {
          "outcomeId": "1060",
          "playerKey": "0",
          "playerName": null,
          "price": 2.17,
          "changedAt": "2026-04-27T17:54:55.682Z",
          "bookmakerOutcomeId": "89522009-df4e-5b04-a4b8-84a880d2d497"
        }
      ]
    },
    {
      "marketId": "1068",
      "bookmakerMarketId": "c52fa1d4-caf7-5a3b-a656-e47150303abc",
      "outcomes": [
        {
          "outcomeId": "1068",
          "playerKey": "0",
          "playerName": null,
          "price": 1.48,
          "changedAt": "2026-04-27T17:54:55.682Z",
          "bookmakerOutcomeId": "ade681be-f9c6-5408-8cea-20de96fc0b27"
        },
        {
          "outcomeId": "1069",
          "playerKey": "0",
          "playerName": null,
          "price": 2.55,
          "changedAt": "2026-04-27T17:54:55.682Z",
          "bookmakerOutcomeId": "4e6c0fab-06b7-5268-8e54-01a11195da6e"
        }
      ]
    },
    {
      "marketId": "1076",
      "bookmakerMarketId": "8ac81646-b845-5d21-a9a4-66154192d244",
      "outcomes": [
        {
          "outcomeId": "1076",
          "playerKey": "0",
          "playerName": null,
          "price": 1.15,
          "changedAt": "2026-04-27T17:54:55.682Z",
          "bookmakerOutcomeId": "c4e7f14d-336d-5386-a90e-c21f090c8298"
        },
        {
          "outcomeId": "1077",
          "playerKey": "0",
          "playerName": null,
          "price": 5.1,
          "changedAt": "2026-04-27T17:54:55.682Z",
          "bookmakerOutcomeId": "1d592cc7-54b9-5b38-b212-9299bdc82d19"
        }
      ]
    },
    {
      "marketId": "1084",
      "bookmakerMarketId": "839d8bc5-5263-549f-a103-cc3ea9b6b65c",
      "outcomes": [
        {
          "outcomeId": "1084",
          "playerKey": "0",
          "playerName": null,
          "price": 1.04,
          "changedAt": "2026-04-26T22:37:52.679Z",
          "bookmakerOutcomeId": "a0571143-76eb-55af-a55e-5280e85997d2"
        },
        {
          "outcomeId": "1085",
          "playerKey": "0",
          "playerName": null,
          "price": 10,
          "changedAt": "2026-04-27T17:54:55.682Z",
          "bookmakerOutcomeId": "2130632c-d745-5820-a44c-925163e8797d"
        }
      ]
    },
    {
      "marketId": "10140",
      "bookmakerMarketId": "06d3afd7-7d90-5055-9857-838ee30f4d4f",
      "outcomes": [
        {
          "outcomeId": "10140",
          "playerKey": "0",
          "playerName": null,
          "price": 2.17,
          "changedAt": "2026-04-27T17:54:55.682Z",
          "bookmakerOutcomeId": "7f6605f9-1657-5e63-a80c-c9d487e36359"
        },
        {
          "outcomeId": "10142",
          "playerKey": "0",
          "playerName": null,
          "price": 2.55,
          "changedAt": "2026-04-27T17:54:55.682Z",
          "bookmakerOutcomeId": "e2fd3090-cc30-5d8e-b668-39987cb1853e"
        },
        {
          "outcomeId": "10141",
          "playerKey": "0",
          "playerName": null,
          "price": 4,
          "changedAt": "2026-04-27T17:54:55.682Z",
          "bookmakerOutcomeId": "3ec20b17-b551-52f3-9027-d18367c6975a"
        }
      ]
    },
    {
      "marketId": "10143",
      "bookmakerMarketId": "27625027-d7c8-5721-b24a-017db0605dc0",
      "outcomes": [
        {
          "outcomeId": "10145",
          "playerKey": "0",
          "playerName": null,
          "price": 1.64,
          "changedAt": "2026-04-27T17:54:55.682Z",
          "bookmakerOutcomeId": "4c5a0a2d-74a7-5952-9f75-fea9683534db"
        },
        {
          "outcomeId": "10143",
          "playerKey": "0",
          "playerName": null,
          "price": 3.7,
          "changedAt": "2026-04-27T17:54:55.682Z",
          "bookmakerOutcomeId": "480c308a-310d-5fdc-bfbd-b13b61bf7107"
        },
        {
          "outcomeId": "10144",
          "playerKey": "0",
          "playerName": null,
          "price": 4.5,
          "changedAt": "2026-04-27T17:54:55.682Z",
          "bookmakerOutcomeId": "e90464e0-e700-59aa-b841-818f361806be"
        }
      ]
    },
    {
      "marketId": "10146",
      "bookmakerMarketId": "7c9cfb4c-b420-54ff-a107-010b223337fc",
      "outcomes": [
        {
          "outcomeId": "10148",
          "playerKey": "0",
          "playerName": null,
          "price": 1.25,
          "changedAt": "2026-04-27T17:54:55.682Z",
          "bookmakerOutcomeId": "07da4251-e26c-5817-b152-76e4e7a4d53b"
        },
        {
          "outcomeId": "10147",
          "playerKey": "0",
          "playerName": null,
          "price": 6.3,
          "changedAt": "2026-04-27T17:54:55.682Z",
          "bookmakerOutcomeId": "c511db4b-94f0-5d80-b14a-b573c3446d5f"
        },
        {
          "outcomeId": "10146",
          "playerKey": "0",
          "playerName": null,
          "price": 6.8,
          "changedAt": "2026-04-27T17:54:55.682Z",
          "bookmakerOutcomeId": "bd9a200f-7cd0-5452-a5af-88b65f84e5ff"
        }
      ]
    },
    {
      "marketId": "10149",
      "bookmakerMarketId": "5943a002-1312-58de-a9cb-c788b2a9179e",
      "outcomes": [
        {
          "outcomeId": "10151",
          "playerKey": "0",
          "playerName": null,
          "price": 1.08,
          "changedAt": "2026-04-27T17:54:55.682Z",
          "bookmakerOutcomeId": "dbaf5302-ae53-59e7-9b53-b4cfae446260"
        },
        {
          "outcomeId": "10150",
          "playerKey": "0",
          "playerName": null,
          "price": 10,
          "changedAt": "2026-04-27T17:54:55.682Z",
          "bookmakerOutcomeId": "107373cb-3daa-51d4-a748-d2bbbc11735d"
        },
        {
          "outcomeId": "10149",
          "playerKey": "0",
          "playerName": null,
          "price": 14,
          "changedAt": "2026-04-27T17:54:55.682Z",
          "bookmakerOutcomeId": "27ae29fa-1a5a-554f-aab9-17aa1ea91747"
        }
      ]
    },
    {
      "marketId": "10152",
      "bookmakerMarketId": "85efa629-881f-53c4-bb9d-739d304ddc96",
      "outcomes": [
        {
          "outcomeId": "10154",
          "playerKey": "0",
          "playerName": null,
          "price": 1.02,
          "changedAt": "2026-04-26T22:37:52.679Z",
          "bookmakerOutcomeId": "bd8913cb-e029-5f6a-912b-2103793bef8b"
        },
        {
          "outcomeId": "10153",
          "playerKey": "0",
          "playerName": null,
          "price": 19,
          "changedAt": "2026-04-27T17:54:55.682Z",
          "bookmakerOutcomeId": "f2a1f7ac-3287-517c-aa13-2166bd4205db"
        },
        {
          "outcomeId": "10152",
          "playerKey": "0",
          "playerName": null,
          "price": 30,
          "changedAt": "2026-04-27T17:54:55.682Z",
          "bookmakerOutcomeId": "84443287-f15e-57a8-8ee6-bca2dfa03374"
        }
      ]
    },
    {
      "marketId": "10208",
      "bookmakerMarketId": "28d10bf6-fc30-541e-9aad-b08b61769913",
      "outcomes": [
        {
          "outcomeId": "10208",
          "playerKey": "0",
          "playerName": null,
          "price": 1.85,
          "changedAt": "2026-04-27T17:54:55.682Z",
          "bookmakerOutcomeId": "7f68686b-52c4-5f2c-9a7d-3f1f12c25484"
        },
        {
          "outcomeId": "10209",
          "playerKey": "0",
          "playerName": null,
          "price": 2.8,
          "changedAt": "2026-04-27T17:54:55.682Z",
          "bookmakerOutcomeId": "10d07cee-e0ee-540b-b7e0-379154aa38cd"
        },
        {
          "outcomeId": "10210",
          "playerKey": "0",
          "playerName": null,
          "price": 5.15,
          "changedAt": "2026-04-27T17:54:55.682Z",
          "bookmakerOutcomeId": "ff79052d-d439-5884-8d52-d9dd5f410dc5"
        }
      ]
    },
    {
      "marketId": "10211",
      "bookmakerMarketId": "fe96b778-f2c0-52e0-80bb-e0c8754ad6b7",
      "outcomes": [
        {
          "outcomeId": "10211",
          "playerKey": "0",
          "playerName": null,
          "price": 1.77,
          "changedAt": "2026-04-27T17:54:55.682Z",
          "bookmakerOutcomeId": "f6e7340d-705f-5f04-a524-47af4e5bd717"
        },
        {
          "outcomeId": "10212",
          "playerKey": "0",
          "playerName": null,
          "price": 3.2,
          "changedAt": "2026-04-27T17:54:55.682Z",
          "bookmakerOutcomeId": "ec5d8691-412a-5941-896c-5ac167832f07"
        },
        {
          "outcomeId": "10213",
          "playerKey": "0",
          "playerName": null,
          "price": 4.7,
          "changedAt": "2026-04-27T17:54:55.682Z",
          "bookmakerOutcomeId": "bd592d37-be3d-543f-9e53-942ca80a0049"
        }
      ]
    },
    {
      "marketId": "10224",
      "bookmakerMarketId": "7730c85a-792f-5bdd-a626-3df575c69949",
      "outcomes": [
        {
          "outcomeId": "10224",
          "playerKey": "0",
          "playerName": null,
          "price": 1.06,
          "changedAt": "2026-04-26T22:37:52.679Z",
          "bookmakerOutcomeId": "9a30daa8-c53d-5d68-a60d-70db249fdf73"
        },
        {
          "outcomeId": "10225",
          "playerKey": "0",
          "playerName": null,
          "price": 8.3,
          "changedAt": "2026-04-27T17:54:55.682Z",
          "bookmakerOutcomeId": "7ba62909-73ef-57ea-b7bf-473292bc75c9"
        }
      ]
    },
    {
      "marketId": "10226",
      "bookmakerMarketId": "d5e99ef2-85a9-5134-88f8-fa067cbf7409",
      "outcomes": [
        {
          "outcomeId": "10226",
          "playerKey": "0",
          "playerName": null,
          "price": 1.36,
          "changedAt": "2026-04-27T17:54:55.682Z",
          "bookmakerOutcomeId": "c6731784-1255-5133-bd9d-1e7e1f97dcc3"
        },
        {
          "outcomeId": "10227",
          "playerKey": "0",
          "playerName": null,
          "price": 3,
          "changedAt": "2026-04-27T17:54:55.682Z",
          "bookmakerOutcomeId": "aa491bd5-6c09-5e4f-8c40-2a85298e0704"
        }
      ]
    },
    {
      "marketId": "10228",
      "bookmakerMarketId": "30067c7c-cbdc-58c2-898a-cb5d4ce5fab0",
      "outcomes": [
        {
          "outcomeId": "10229",
          "playerKey": "0",
          "playerName": null,
          "price": 1.68,
          "changedAt": "2026-04-27T17:54:55.682Z",
          "bookmakerOutcomeId": "fe91d0e4-f847-50f8-8759-e19ca0db6c82"
        },
        {
          "outcomeId": "10228",
          "playerKey": "0",
          "playerName": null,
          "price": 2.1,
          "changedAt": "2026-04-27T17:54:55.682Z",
          "bookmakerOutcomeId": "f621ffd9-2de0-5efb-b51f-606617b96353"
        }
      ]
    },
    {
      "marketId": "10230",
      "bookmakerMarketId": "fdf94ad4-ae0a-5230-b859-2ddbff2d076a",
      "outcomes": [
        {
          "outcomeId": "10231",
          "playerKey": "0",
          "playerName": null,
          "price": 1.23,
          "changedAt": "2026-04-27T17:54:55.682Z",
          "bookmakerOutcomeId": "4fa842b2-c649-5da4-bc67-b38f0780601c"
        },
        {
          "outcomeId": "10230",
          "playerKey": "0",
          "playerName": null,
          "price": 3.85,
          "changedAt": "2026-04-27T17:54:55.682Z",
          "bookmakerOutcomeId": "1cc81046-e1e3-572a-8caa-05f4909f02a4"
        }
      ]
    },
    {
      "marketId": "10232",
      "bookmakerMarketId": "c5b0e5b7-33ca-58ec-bbbb-fbc7f118ae54",
      "outcomes": [
        {
          "outcomeId": "10233",
          "playerKey": "0",
          "playerName": null,
          "price": 1.07,
          "changedAt": "2026-04-27T17:54:55.682Z",
          "bookmakerOutcomeId": "931d1d84-83ab-5f22-b7fb-c8423c2227e0"
        },
        {
          "outcomeId": "10232",
          "playerKey": "0",
          "playerName": null,
          "price": 7.5,
          "changedAt": "2026-04-27T17:54:55.682Z",
          "bookmakerOutcomeId": "017ec566-3036-5e6e-a872-389a2870be31"
        }
      ]
    },
    {
      "marketId": "10240",
      "bookmakerMarketId": "685a04ff-1b85-56b8-9d5c-15527ecf60a1",
      "outcomes": [
        {
          "outcomeId": "10240",
          "playerKey": "0",
          "playerName": null,
          "price": 1.37,
          "changedAt": "2026-04-27T17:54:55.682Z",
          "bookmakerOutcomeId": "e971cb70-2c04-5cda-8810-f076eb95ff88"
        },
        {
          "outcomeId": "10241",
          "playerKey": "0",
          "playerName": null,
          "price": 2.92,
          "changedAt": "2026-04-27T17:54:55.682Z",
          "bookmakerOutcomeId": "38b86aa5-c100-5cfa-bebc-a0d0adfc417f"
        }
      ]
    },
    {
      "marketId": "10242",
      "bookmakerMarketId": "7a2ff1be-f734-5ad6-b592-f6d2849b29f2",
      "outcomes": [
        {
          "outcomeId": "10243",
          "playerKey": "0",
          "playerName": null,
          "price": 1.41,
          "changedAt": "2026-04-27T17:54:55.682Z",
          "bookmakerOutcomeId": "08b88b25-e6d3-565f-8f3f-4ef47fe7a87c"
        },
        {
          "outcomeId": "10242",
          "playerKey": "0",
          "playerName": null,
          "price": 2.75,
          "changedAt": "2026-04-27T17:54:55.682Z",
          "bookmakerOutcomeId": "df314961-602d-5807-aa33-807fbe834127"
        }
      ]
    },
    {
      "marketId": "10244",
      "bookmakerMarketId": "c35ac6e3-6aef-5a56-a3b9-d624038e5b3f",
      "outcomes": [
        {
          "outcomeId": "10245",
          "playerKey": "0",
          "playerName": null,
          "price": 1.09,
          "changedAt": "2026-04-26T22:37:52.679Z",
          "bookmakerOutcomeId": "83976ac9-beb8-5c17-b00f-edf210cb830c"
        },
        {
          "outcomeId": "10244",
          "playerKey": "0",
          "playerName": null,
          "price": 6.7,
          "changedAt": "2026-04-27T17:54:55.682Z",
          "bookmakerOutcomeId": "6b2c6161-1b64-5305-8b9b-85a6ba3394de"
        }
      ]
    },
    {
      "marketId": "10246",
      "bookmakerMarketId": "f2c1d9e9-8137-55d3-bc15-fb0814b681f3",
      "outcomes": [
        {
          "outcomeId": "10247",
          "playerKey": "0",
          "playerName": null,
          "price": 1.01,
          "changedAt": "2026-04-26T22:37:52.679Z",
          "bookmakerOutcomeId": "0a4e9f17-9794-59f6-87ee-80ff98438ce8"
        },
        {
          "outcomeId": "10246",
          "playerKey": "0",
          "playerName": null,
          "price": 18,
          "changedAt": "2026-04-27T17:54:55.682Z",
          "bookmakerOutcomeId": "89487568-c5fe-544c-88cb-491db5b2eb09"
        }
      ]
    },
    {
      "marketId": "10248",
      "bookmakerMarketId": "bf02c16a-dd01-5833-9a00-30b35a1e3211",
      "outcomes": [
        {
          "outcomeId": "10248",
          "playerKey": "0",
          "playerName": null,
          "price": 50,
          "changedAt": "2026-04-26T22:37:52.679Z",
          "bookmakerOutcomeId": "9fbe6cfe-367a-50d3-bcf9-cdde082188e7"
        }
      ]
    },
    {
      "marketId": "10256",
      "bookmakerMarketId": "10dd2bd9-6137-555d-8ce1-72c451e5f7bf",
      "outcomes": [
        {
          "outcomeId": "10256",
          "playerKey": "0",
          "playerName": null,
          "price": 1.22,
          "changedAt": "2026-04-26T22:37:52.679Z",
          "bookmakerOutcomeId": "999a264b-076c-5da2-bd96-48f59719c7ce"
        },
        {
          "outcomeId": "10257",
          "playerKey": "0",
          "playerName": null,
          "price": 4.35,
          "changedAt": "2026-04-26T22:37:52.679Z",
          "bookmakerOutcomeId": "f7499beb-3b2b-5121-8eef-e0edae613146"
        }
      ]
    },
    {
      "marketId": "10258",
      "bookmakerMarketId": "b998bfed-c595-5786-af3d-d533892595d4",
      "outcomes": [
        {
          "outcomeId": "10259",
          "playerKey": "0",
          "playerName": null,
          "price": 1.8,
          "changedAt": "2026-04-26T22:37:52.679Z",
          "bookmakerOutcomeId": "8b73ccc6-8c9d-53eb-9727-4d1eb65baa26"
        },
        {
          "outcomeId": "10258",
          "playerKey": "0",
          "playerName": null,
          "price": 2.02,
          "changedAt": "2026-04-26T22:37:52.679Z",
          "bookmakerOutcomeId": "ec3fbf85-3b23-5107-8e9a-a57f0de5bcbe"
        }
      ]
    },
    {
      "marketId": "10260",
      "bookmakerMarketId": "d252d50e-5ac0-5b10-8244-c2dec1fbbec6",
      "outcomes": [
        {
          "outcomeId": "10261",
          "playerKey": "0",
          "playerName": null,
          "price": 1.23,
          "changedAt": "2026-04-26T22:37:52.679Z",
          "bookmakerOutcomeId": "a0523895-189c-5c22-9327-09b1471ab554"
        },
        {
          "outcomeId": "10260",
          "playerKey": "0",
          "playerName": null,
          "price": 4.2,
          "changedAt": "2026-04-26T22:37:52.679Z",
          "bookmakerOutcomeId": "b2023a00-403c-5c14-a2b2-802171efa4b9"
        }
      ]
    },
    {
      "marketId": "10262",
      "bookmakerMarketId": "10602fad-be0e-561f-b1bc-83e7bdb32e66",
      "outcomes": [
        {
          "outcomeId": "10263",
          "playerKey": "0",
          "playerName": null,
          "price": 1.06,
          "changedAt": "2026-04-26T22:37:52.679Z",
          "bookmakerOutcomeId": "ee755f7a-8fe0-5042-89b8-5623f4fe8768"
        },
        {
          "outcomeId": "10262",
          "playerKey": "0",
          "playerName": null,
          "price": 9.9,
          "changedAt": "2026-04-26T22:37:52.679Z",
          "bookmakerOutcomeId": "ae7908bf-9116-5891-871a-39acd086063d"
        }
      ]
    },
    {
      "marketId": "10264",
      "bookmakerMarketId": "f5e47771-243e-5b9d-a196-7c40db938585",
      "outcomes": [
        {
          "outcomeId": "10265",
          "playerKey": "0",
          "playerName": null,
          "price": 1.01,
          "changedAt": "2026-04-26T22:37:52.679Z",
          "bookmakerOutcomeId": "78146c38-38cc-5ceb-80d3-90e86dd7db86"
        },
        {
          "outcomeId": "10264",
          "playerKey": "0",
          "playerName": null,
          "price": 26,
          "changedAt": "2026-04-26T22:37:52.679Z",
          "bookmakerOutcomeId": "f0a458a3-c572-5dd8-9c0e-1d2e7edfd225"
        }
      ]
    },
    {
      "marketId": "10284",
      "bookmakerMarketId": "c45a77f5-8a21-59c2-a0cf-e212f6cbedeb",
      "outcomes": [
        {
          "outcomeId": "10284",
          "playerKey": "0",
          "playerName": null,
          "price": 1.06,
          "changedAt": "2026-04-26T22:37:52.679Z",
          "bookmakerOutcomeId": "f85afbe4-f5dc-53cf-b6c1-522ac1614379"
        },
        {
          "outcomeId": "10285",
          "playerKey": "0",
          "playerName": null,
          "price": 8.5,
          "changedAt": "2026-04-27T17:54:55.682Z",
          "bookmakerOutcomeId": "fabaee4f-4262-543a-8bbb-9136f30160be"
        }
      ]
    },
    {
      "marketId": "10286",
      "bookmakerMarketId": "632119e8-186f-5583-8ed7-747ef6ef3e3d",
      "outcomes": [
        {
          "outcomeId": "10286",
          "playerKey": "0",
          "playerName": null,
          "price": 1.37,
          "changedAt": "2026-04-27T17:54:55.682Z",
          "bookmakerOutcomeId": "8fa9113d-9f73-516b-8432-fe04874df001"
        },
        {
          "outcomeId": "10287",
          "playerKey": "0",
          "playerName": null,
          "price": 2.92,
          "changedAt": "2026-04-27T17:54:55.682Z",
          "bookmakerOutcomeId": "31c328fe-2fb6-5c08-acb8-4e31b805003f"
        }
      ]
    },
    {
      "marketId": "10288",
      "bookmakerMarketId": "10b85a9a-6c6d-5c24-b863-c9634b299a1f",
      "outcomes": [
        {
          "outcomeId": "10288",
          "playerKey": "0",
          "playerName": null,
          "price": 1.42,
          "changedAt": "2026-04-27T17:54:55.682Z",
          "bookmakerOutcomeId": "0e2303ba-1a77-59eb-a072-154fbca9b180"
        },
        {
          "outcomeId": "10289",
          "playerKey": "0",
          "playerName": null,
          "price": 2.72,
          "changedAt": "2026-04-27T17:54:55.682Z",
          "bookmakerOutcomeId": "f09f1777-b060-570f-8166-7bc7617ae90d"
        }
      ]
    },
    {
      "marketId": "10290",
      "bookmakerMarketId": "fa4a74e1-8792-573f-82e9-915273c0b163",
      "outcomes": [
        {
          "outcomeId": "10291",
          "playerKey": "0",
          "playerName": null,
          "price": 1.54,
          "changedAt": "2026-04-27T17:54:55.682Z",
          "bookmakerOutcomeId": "5fa22cae-fd0c-5545-8b92-a847fa8f671f"
        },
        {
          "outcomeId": "10290",
          "playerKey": "0",
          "playerName": null,
          "price": 2.37,
          "changedAt": "2026-04-27T17:54:55.682Z",
          "bookmakerOutcomeId": "119933eb-b689-5a60-a4ba-a3a40caa4c7a"
        }
      ]
    },
    {
      "marketId": "10292",
      "bookmakerMarketId": "a54d85a1-10a0-588c-88d0-fd0ba8b9922d",
      "outcomes": [
        {
          "outcomeId": "10292",
          "playerKey": "0",
          "playerName": null,
          "price": 1.29,
          "changedAt": "2026-04-27T17:54:55.682Z",
          "bookmakerOutcomeId": "5593d307-2992-5fba-8af1-ebeebb201cc1"
        },
        {
          "outcomeId": "10293",
          "playerKey": "0",
          "playerName": null,
          "price": 3.4,
          "changedAt": "2026-04-27T17:54:55.682Z",
          "bookmakerOutcomeId": "69c0d0c7-fab9-5278-8c0a-d2ab0b80157e"
        }
      ]
    },
    {
      "marketId": "10294",
      "bookmakerMarketId": "df55f625-e76e-5f90-8f5f-4ec3a892b4a1",
      "outcomes": [
        {
          "outcomeId": "10295",
          "playerKey": "0",
          "playerName": null,
          "price": 1.82,
          "changedAt": "2026-04-27T17:54:55.682Z",
          "bookmakerOutcomeId": "9da1b95b-2429-5d64-8cb5-854465e30e40"
        },
        {
          "outcomeId": "10294",
          "playerKey": "0",
          "playerName": null,
          "price": 1.92,
          "changedAt": "2026-04-27T17:54:55.682Z",
          "bookmakerOutcomeId": "f83e124f-7acb-5bec-a6fb-925f049b9908"
        }
      ]
    },
    {
      "marketId": "10300",
      "bookmakerMarketId": "633de0fb-a838-5c7c-8ef6-d6ba39807628",
      "outcomes": [
        {
          "outcomeId": "10301",
          "playerKey": "0",
          "playerName": null,
          "price": 1.29,
          "changedAt": "2026-04-26T22:37:52.679Z",
          "bookmakerOutcomeId": "4d75bbe1-bf73-5319-89a2-90de3387e311"
        },
        {
          "outcomeId": "10300",
          "playerKey": "0",
          "playerName": null,
          "price": 3.4,
          "changedAt": "2026-04-26T22:37:52.679Z",
          "bookmakerOutcomeId": "c13c74a6-f06e-577e-8ed0-b0f3df2ff865"
        }
      ]
    },
    {
      "marketId": "10302",
      "bookmakerMarketId": "32e9161a-3441-5741-a9a2-30e9f79fca83",
      "outcomes": [
        {
          "outcomeId": "10303",
          "playerKey": "0",
          "playerName": null,
          "price": 1.49,
          "changedAt": "2026-04-26T22:37:52.679Z",
          "bookmakerOutcomeId": "f9d5e00e-9755-5209-aa7c-8a86a49ecef9"
        },
        {
          "outcomeId": "10302",
          "playerKey": "0",
          "playerName": null,
          "price": 2.5,
          "changedAt": "2026-04-26T22:37:52.679Z",
          "bookmakerOutcomeId": "1b149ff5-e450-5070-ae99-223dc9ec0b83"
        }
      ]
    }
  ]
}