{
  "uiSchemaVersion": 2,
  "fixtureId": "id1000032566886762",
  "startTime": "2026-05-10T21:30:00.000Z",
  "day": "2026-05-10",
  "tournamentId": 325,
  "tournamentName": "Brasileiro Serie A",
  "categoryName": "Brazil",
  "home": "Santos FC SP",
  "away": "Red Bull Bragantino SP",
  "bookmakerKey": "superbet.ro",
  "fixturePath": "https://superbet.com/offer-event/e-12034226",
  "featuredMarkets": {
    "ft1x2": {
      "key": "ft1x2",
      "label": "1X2 (FT)",
      "marketId": "10137",
      "bookmakerMarketId": "859407e0-171f-5793-acc3-b17c0e1e73f5",
      "outcomes": [
        {
          "key": "HOME",
          "label": "Home",
          "outcomeId": "10137",
          "price": 1.28,
          "changedAt": "2026-04-27T15:54:20.677Z"
        },
        {
          "key": "DRAW",
          "label": "Draw",
          "outcomeId": "10138",
          "price": 5.2,
          "changedAt": "2026-04-27T15:54:20.677Z"
        },
        {
          "key": "AWAY",
          "label": "Away",
          "outcomeId": "10139",
          "price": 7.5,
          "changedAt": "2026-04-27T15:54:20.677Z"
        }
      ]
    },
    "btts": {
      "key": "btts",
      "label": "BTTS",
      "marketId": "104",
      "bookmakerMarketId": "7bc0b9fc-eff0-5b9c-a1c0-2b57593bef34",
      "outcomes": [
        {
          "key": "YES",
          "label": "Yes",
          "outcomeId": "104",
          "price": 1.82,
          "changedAt": "2026-04-27T15:54:20.677Z"
        },
        {
          "key": "NO",
          "label": "No",
          "outcomeId": "105",
          "price": 1.92,
          "changedAt": "2026-04-27T15:54:20.677Z"
        }
      ]
    },
    "doubleChance": null
  },
  "selectionIndex": {
    "BTTS|YES": {
      "market": "BTTS",
      "selection": "YES",
      "label": "BTTS YES",
      "marketId": "104",
      "outcomeId": "104",
      "bookmakerMarketId": "7bc0b9fc-eff0-5b9c-a1c0-2b57593bef34",
      "price": 1.82,
      "changedAt": "2026-04-27T15:54:20.677Z"
    },
    "BTTS|NO": {
      "market": "BTTS",
      "selection": "NO",
      "label": "BTTS NO",
      "marketId": "104",
      "outcomeId": "105",
      "bookmakerMarketId": "7bc0b9fc-eff0-5b9c-a1c0-2b57593bef34",
      "price": 1.92,
      "changedAt": "2026-04-27T15:54:20.677Z"
    },
    "Double Chance|1X": {
      "market": "Double Chance",
      "selection": "1X",
      "label": "Double Chance 1X",
      "marketId": "101902",
      "outcomeId": "101902",
      "bookmakerMarketId": null,
      "price": null,
      "changedAt": null
    },
    "Double Chance|12": {
      "market": "Double Chance",
      "selection": "12",
      "label": "Double Chance 12",
      "marketId": "101902",
      "outcomeId": "101903",
      "bookmakerMarketId": null,
      "price": null,
      "changedAt": null
    },
    "Double Chance|X2": {
      "market": "Double Chance",
      "selection": "X2",
      "label": "Double Chance X2",
      "marketId": "101902",
      "outcomeId": "101904",
      "bookmakerMarketId": null,
      "price": null,
      "changedAt": null
    },
    "Goals 1.5|OVER": {
      "market": "Goals 1.5",
      "selection": "OVER",
      "label": "Goals 1.5 OVER",
      "marketId": "108",
      "outcomeId": "108",
      "bookmakerMarketId": "a48b0882-dda4-5f8c-b098-706ac3c0d0ef",
      "price": 1.33,
      "changedAt": "2026-04-27T15:54:20.677Z"
    },
    "Goals 1.5|UNDER": {
      "market": "Goals 1.5",
      "selection": "UNDER",
      "label": "Goals 1.5 UNDER",
      "marketId": "108",
      "outcomeId": "109",
      "bookmakerMarketId": "a48b0882-dda4-5f8c-b098-706ac3c0d0ef",
      "price": 3.3,
      "changedAt": "2026-04-27T15:54:20.677Z"
    },
    "Goals 2.5|OVER": {
      "market": "Goals 2.5",
      "selection": "OVER",
      "label": "Goals 2.5 OVER",
      "marketId": "1010",
      "outcomeId": "1010",
      "bookmakerMarketId": "38b59486-a35d-5c40-826a-07c36e8b5bf4",
      "price": 2.05,
      "changedAt": "2026-04-27T15:54:20.677Z"
    },
    "Goals 2.5|UNDER": {
      "market": "Goals 2.5",
      "selection": "UNDER",
      "label": "Goals 2.5 UNDER",
      "marketId": "1010",
      "outcomeId": "1011",
      "bookmakerMarketId": "38b59486-a35d-5c40-826a-07c36e8b5bf4",
      "price": 1.78,
      "changedAt": "2026-04-27T15:54:20.677Z"
    },
    "Goals 3.5|OVER": {
      "market": "Goals 3.5",
      "selection": "OVER",
      "label": "Goals 3.5 OVER",
      "marketId": "1012",
      "outcomeId": "1012",
      "bookmakerMarketId": "de3e057e-1cf2-557c-a03b-1787da8b8721",
      "price": 3.6,
      "changedAt": "2026-04-27T15:54:20.677Z"
    },
    "Goals 3.5|UNDER": {
      "market": "Goals 3.5",
      "selection": "UNDER",
      "label": "Goals 3.5 UNDER",
      "marketId": "1012",
      "outcomeId": "1013",
      "bookmakerMarketId": "de3e057e-1cf2-557c-a03b-1787da8b8721",
      "price": 1.3,
      "changedAt": "2026-04-27T15:54:20.677Z"
    },
    "Goals 4.5|OVER": {
      "market": "Goals 4.5",
      "selection": "OVER",
      "label": "Goals 4.5 OVER",
      "marketId": "1014",
      "outcomeId": "1014",
      "bookmakerMarketId": "9775debf-36f2-50a1-b872-5f2e241dd9e7",
      "price": 7.2,
      "changedAt": "2026-04-27T15:54:20.677Z"
    },
    "Goals 4.5|UNDER": {
      "market": "Goals 4.5",
      "selection": "UNDER",
      "label": "Goals 4.5 UNDER",
      "marketId": "1014",
      "outcomeId": "1015",
      "bookmakerMarketId": "9775debf-36f2-50a1-b872-5f2e241dd9e7",
      "price": 1.1,
      "changedAt": "2026-04-26T22:44:18.354Z"
    },
    "Corners 8.5|OVER": {
      "market": "Corners 8.5",
      "selection": "OVER",
      "label": "Corners 8.5 OVER",
      "marketId": "10799",
      "outcomeId": "10799",
      "bookmakerMarketId": null,
      "price": null,
      "changedAt": null
    },
    "Corners 8.5|UNDER": {
      "market": "Corners 8.5",
      "selection": "UNDER",
      "label": "Corners 8.5 UNDER",
      "marketId": "10799",
      "outcomeId": "10800",
      "bookmakerMarketId": null,
      "price": null,
      "changedAt": null
    },
    "Corners 9.5|OVER": {
      "market": "Corners 9.5",
      "selection": "OVER",
      "label": "Corners 9.5 OVER",
      "marketId": "10803",
      "outcomeId": "10803",
      "bookmakerMarketId": null,
      "price": null,
      "changedAt": null
    },
    "Corners 9.5|UNDER": {
      "market": "Corners 9.5",
      "selection": "UNDER",
      "label": "Corners 9.5 UNDER",
      "marketId": "10803",
      "outcomeId": "10804",
      "bookmakerMarketId": null,
      "price": null,
      "changedAt": null
    },
    "Corners 10.5|OVER": {
      "market": "Corners 10.5",
      "selection": "OVER",
      "label": "Corners 10.5 OVER",
      "marketId": "10807",
      "outcomeId": "10807",
      "bookmakerMarketId": null,
      "price": null,
      "changedAt": null
    },
    "Corners 10.5|UNDER": {
      "market": "Corners 10.5",
      "selection": "UNDER",
      "label": "Corners 10.5 UNDER",
      "marketId": "10807",
      "outcomeId": "10808",
      "bookmakerMarketId": null,
      "price": null,
      "changedAt": null
    },
    "Cards 3.5|OVER": {
      "market": "Cards 3.5",
      "selection": "OVER",
      "label": "Cards 3.5 OVER",
      "marketId": "10926",
      "outcomeId": "10926",
      "bookmakerMarketId": null,
      "price": null,
      "changedAt": null
    },
    "Cards 3.5|UNDER": {
      "market": "Cards 3.5",
      "selection": "UNDER",
      "label": "Cards 3.5 UNDER",
      "marketId": "10926",
      "outcomeId": "10927",
      "bookmakerMarketId": null,
      "price": null,
      "changedAt": null
    },
    "Cards 4.5|OVER": {
      "market": "Cards 4.5",
      "selection": "OVER",
      "label": "Cards 4.5 OVER",
      "marketId": "10930",
      "outcomeId": "10930",
      "bookmakerMarketId": null,
      "price": null,
      "changedAt": null
    },
    "Cards 4.5|UNDER": {
      "market": "Cards 4.5",
      "selection": "UNDER",
      "label": "Cards 4.5 UNDER",
      "marketId": "10930",
      "outcomeId": "10931",
      "bookmakerMarketId": null,
      "price": null,
      "changedAt": null
    },
    "Cards 5.5|OVER": {
      "market": "Cards 5.5",
      "selection": "OVER",
      "label": "Cards 5.5 OVER",
      "marketId": "10934",
      "outcomeId": "10934",
      "bookmakerMarketId": null,
      "price": null,
      "changedAt": null
    },
    "Cards 5.5|UNDER": {
      "market": "Cards 5.5",
      "selection": "UNDER",
      "label": "Cards 5.5 UNDER",
      "marketId": "10934",
      "outcomeId": "10935",
      "bookmakerMarketId": null,
      "price": null,
      "changedAt": null
    }
  },
  "markets": [
    {
      "marketId": "104",
      "bookmakerMarketId": "7bc0b9fc-eff0-5b9c-a1c0-2b57593bef34",
      "outcomes": [
        {
          "outcomeId": "104",
          "playerKey": "0",
          "playerName": null,
          "price": 1.82,
          "changedAt": "2026-04-27T15:54:20.677Z",
          "bookmakerOutcomeId": "fe7e56d7-8013-5e89-87a0-4e0a3e102b55"
        },
        {
          "outcomeId": "105",
          "playerKey": "0",
          "playerName": null,
          "price": 1.92,
          "changedAt": "2026-04-27T15:54:20.677Z",
          "bookmakerOutcomeId": "e023fc01-a31e-5ff1-a1c1-7e42b6bfecdd"
        }
      ]
    },
    {
      "marketId": "106",
      "bookmakerMarketId": "5ad70794-0fdb-5a86-be22-696dd29aa91f",
      "outcomes": [
        {
          "outcomeId": "106",
          "playerKey": "0",
          "playerName": null,
          "price": 1.06,
          "changedAt": "2026-04-26T22:44:18.354Z",
          "bookmakerOutcomeId": "1d79b85a-4ae3-5e82-a29f-d9b788b39548"
        },
        {
          "outcomeId": "107",
          "playerKey": "0",
          "playerName": null,
          "price": 9.3,
          "changedAt": "2026-04-26T22:44:18.354Z",
          "bookmakerOutcomeId": "4840b916-1b8b-5580-9974-5c86245ef2af"
        }
      ]
    },
    {
      "marketId": "108",
      "bookmakerMarketId": "a48b0882-dda4-5f8c-b098-706ac3c0d0ef",
      "outcomes": [
        {
          "outcomeId": "108",
          "playerKey": "0",
          "playerName": null,
          "price": 1.33,
          "changedAt": "2026-04-27T15:54:20.677Z",
          "bookmakerOutcomeId": "6112a5aa-5726-5884-97ab-286d0364b7d1"
        },
        {
          "outcomeId": "109",
          "playerKey": "0",
          "playerName": null,
          "price": 3.3,
          "changedAt": "2026-04-27T15:54:20.677Z",
          "bookmakerOutcomeId": "2f8b0a03-169d-5c6f-9be6-a39055e51dd5"
        }
      ]
    },
    {
      "marketId": "1010",
      "bookmakerMarketId": "38b59486-a35d-5c40-826a-07c36e8b5bf4",
      "outcomes": [
        {
          "outcomeId": "1011",
          "playerKey": "0",
          "playerName": null,
          "price": 1.78,
          "changedAt": "2026-04-27T15:54:20.677Z",
          "bookmakerOutcomeId": "8c3ef5c3-c0fc-570a-8b1f-74d1663231ec"
        },
        {
          "outcomeId": "1010",
          "playerKey": "0",
          "playerName": null,
          "price": 2.05,
          "changedAt": "2026-04-27T15:54:20.677Z",
          "bookmakerOutcomeId": "c85a3daf-5c4d-5332-8379-6c1839b5dbf2"
        }
      ]
    },
    {
      "marketId": "1012",
      "bookmakerMarketId": "de3e057e-1cf2-557c-a03b-1787da8b8721",
      "outcomes": [
        {
          "outcomeId": "1013",
          "playerKey": "0",
          "playerName": null,
          "price": 1.3,
          "changedAt": "2026-04-27T15:54:20.677Z",
          "bookmakerOutcomeId": "2faa45c5-9984-5f62-b1de-5daaf4ba55b5"
        },
        {
          "outcomeId": "1012",
          "playerKey": "0",
          "playerName": null,
          "price": 3.6,
          "changedAt": "2026-04-27T15:54:20.677Z",
          "bookmakerOutcomeId": "5daf38c4-b32a-59a3-83c1-6a6dc65596cf"
        }
      ]
    },
    {
      "marketId": "1014",
      "bookmakerMarketId": "9775debf-36f2-50a1-b872-5f2e241dd9e7",
      "outcomes": [
        {
          "outcomeId": "1015",
          "playerKey": "0",
          "playerName": null,
          "price": 1.1,
          "changedAt": "2026-04-26T22:44:18.354Z",
          "bookmakerOutcomeId": "65b050d3-a243-5257-9b4b-f4576a172871"
        },
        {
          "outcomeId": "1014",
          "playerKey": "0",
          "playerName": null,
          "price": 7.2,
          "changedAt": "2026-04-27T15:54:20.677Z",
          "bookmakerOutcomeId": "c1288493-a570-5c9e-a6d0-e353b2696d98"
        }
      ]
    },
    {
      "marketId": "1016",
      "bookmakerMarketId": "e0bbe129-c83a-5963-b064-560c0d52d376",
      "outcomes": [
        {
          "outcomeId": "1017",
          "playerKey": "0",
          "playerName": null,
          "price": 1.03,
          "changedAt": "2026-04-26T22:44:18.354Z",
          "bookmakerOutcomeId": "a2bea4c4-ba52-5cd3-96a1-7598c663aa57"
        },
        {
          "outcomeId": "1016",
          "playerKey": "0",
          "playerName": null,
          "price": 15,
          "changedAt": "2026-04-27T15:54:20.677Z",
          "bookmakerOutcomeId": "fb253adf-7e19-5948-ad6d-35a04f081bc0"
        }
      ]
    },
    {
      "marketId": "1018",
      "bookmakerMarketId": "56419688-cf78-512f-92d6-bc9e126e5db6",
      "outcomes": [
        {
          "outcomeId": "1019",
          "playerKey": "0",
          "playerName": null,
          "price": 1.007,
          "changedAt": "2026-04-26T22:44:18.354Z",
          "bookmakerOutcomeId": "96306c22-f52b-57d1-b929-db692ce12e36"
        },
        {
          "outcomeId": "1018",
          "playerKey": "0",
          "playerName": null,
          "price": 35,
          "changedAt": "2026-04-27T15:54:20.677Z",
          "bookmakerOutcomeId": "4ee89673-4180-5f38-af24-18f9792e84dc"
        }
      ]
    },
    {
      "marketId": "1052",
      "bookmakerMarketId": "595fd0e7-606b-5019-9ddb-6334ad7944bd",
      "outcomes": [
        {
          "outcomeId": "1053",
          "playerKey": "0",
          "playerName": null,
          "price": 1.06,
          "changedAt": "2026-04-26T22:44:18.354Z",
          "bookmakerOutcomeId": "818a52c8-0ffe-56d3-a45e-13def5307d1d"
        },
        {
          "outcomeId": "1052",
          "playerKey": "0",
          "playerName": null,
          "price": 8.1,
          "changedAt": "2026-04-27T15:54:20.677Z",
          "bookmakerOutcomeId": "bc786311-59b8-5f24-bf7d-3a696aae86ea"
        }
      ]
    },
    {
      "marketId": "1060",
      "bookmakerMarketId": "c4744124-824f-5be4-b8a7-5655b612f3a8",
      "outcomes": [
        {
          "outcomeId": "1061",
          "playerKey": "0",
          "playerName": null,
          "price": 1.24,
          "changedAt": "2026-04-27T15:54:20.677Z",
          "bookmakerOutcomeId": "a70736c9-a4c1-5845-aa71-20aa01ca9063"
        },
        {
          "outcomeId": "1060",
          "playerKey": "0",
          "playerName": null,
          "price": 3.85,
          "changedAt": "2026-04-27T15:54:20.677Z",
          "bookmakerOutcomeId": "8824e0a0-3215-5870-98da-760f1ebded42"
        }
      ]
    },
    {
      "marketId": "1068",
      "bookmakerMarketId": "ccc20cdb-f152-5ff6-b260-a912f4b3514e",
      "outcomes": [
        {
          "outcomeId": "1069",
          "playerKey": "0",
          "playerName": null,
          "price": 1.73,
          "changedAt": "2026-04-27T15:54:20.677Z",
          "bookmakerOutcomeId": "6d5064f3-ab9e-5aa3-80e6-8077cae58381"
        },
        {
          "outcomeId": "1068",
          "playerKey": "0",
          "playerName": null,
          "price": 2.02,
          "changedAt": "2026-04-27T15:54:20.677Z",
          "bookmakerOutcomeId": "f332487f-ecd8-587a-bb41-65526f10c364"
        }
      ]
    },
    {
      "marketId": "1076",
      "bookmakerMarketId": "1338a538-9063-5c0e-8730-2a3756ea6c19",
      "outcomes": [
        {
          "outcomeId": "1076",
          "playerKey": "0",
          "playerName": null,
          "price": 1.28,
          "changedAt": "2026-04-27T15:54:20.677Z",
          "bookmakerOutcomeId": "6fba8044-0fea-5165-9ae3-b69d23e1d2ca"
        },
        {
          "outcomeId": "1077",
          "playerKey": "0",
          "playerName": null,
          "price": 3.45,
          "changedAt": "2026-04-27T15:54:20.677Z",
          "bookmakerOutcomeId": "c5a5a3c1-3083-5cea-8f2c-be7fe3a02707"
        }
      ]
    },
    {
      "marketId": "1084",
      "bookmakerMarketId": "72cc7861-d91d-58b4-b01f-066164d3a4c4",
      "outcomes": [
        {
          "outcomeId": "1084",
          "playerKey": "0",
          "playerName": null,
          "price": 1.07,
          "changedAt": "2026-04-26T22:44:18.354Z",
          "bookmakerOutcomeId": "4fb9799c-7b25-5b6e-9586-13c210577bd1"
        },
        {
          "outcomeId": "1085",
          "playerKey": "0",
          "playerName": null,
          "price": 7.5,
          "changedAt": "2026-04-27T15:54:20.677Z",
          "bookmakerOutcomeId": "51e7ddec-a1d4-5d66-a5fb-7d72c3f01e38"
        }
      ]
    },
    {
      "marketId": "10137",
      "bookmakerMarketId": "859407e0-171f-5793-acc3-b17c0e1e73f5",
      "outcomes": [
        {
          "outcomeId": "10137",
          "playerKey": "0",
          "playerName": null,
          "price": 1.28,
          "changedAt": "2026-04-27T15:54:20.677Z",
          "bookmakerOutcomeId": "7583a49f-d73b-587b-a19b-fcdab006a620"
        },
        {
          "outcomeId": "10138",
          "playerKey": "0",
          "playerName": null,
          "price": 5.2,
          "changedAt": "2026-04-27T15:54:20.677Z",
          "bookmakerOutcomeId": "bec21fb6-feb7-5e4a-815e-90ea1d19caa2"
        },
        {
          "outcomeId": "10139",
          "playerKey": "0",
          "playerName": null,
          "price": 7.5,
          "changedAt": "2026-04-27T15:54:20.677Z",
          "bookmakerOutcomeId": "95bf662e-2310-5b92-a463-a121742fba25"
        }
      ]
    },
    {
      "marketId": "10140",
      "bookmakerMarketId": "42ecd5cf-ed99-587f-900f-40315edea0f2",
      "outcomes": [
        {
          "outcomeId": "10142",
          "playerKey": "0",
          "playerName": null,
          "price": 1.73,
          "changedAt": "2026-04-27T15:54:20.677Z",
          "bookmakerOutcomeId": "6f87892b-127a-5ecf-ad10-5cad50a1566e"
        },
        {
          "outcomeId": "10141",
          "playerKey": "0",
          "playerName": null,
          "price": 3.75,
          "changedAt": "2026-04-27T15:54:20.677Z",
          "bookmakerOutcomeId": "19c3981b-7b0b-51ec-94fc-087671b5853d"
        },
        {
          "outcomeId": "10140",
          "playerKey": "0",
          "playerName": null,
          "price": 3.85,
          "changedAt": "2026-04-27T15:54:20.677Z",
          "bookmakerOutcomeId": "164d8be1-28f0-57e8-b950-2a04f40e9a43"
        }
      ]
    },
    {
      "marketId": "10143",
      "bookmakerMarketId": "0c7b5b2f-7139-5ce9-910f-df0e392b2afb",
      "outcomes": [
        {
          "outcomeId": "10145",
          "playerKey": "0",
          "playerName": null,
          "price": 1.24,
          "changedAt": "2026-04-27T15:54:20.677Z",
          "bookmakerOutcomeId": "f264c545-411a-50dc-9729-956fcf206bea"
        },
        {
          "outcomeId": "10144",
          "playerKey": "0",
          "playerName": null,
          "price": 5.8,
          "changedAt": "2026-04-27T15:54:20.677Z",
          "bookmakerOutcomeId": "9a5eb245-83fd-50ad-b8d8-d6f049e73906"
        },
        {
          "outcomeId": "10143",
          "playerKey": "0",
          "playerName": null,
          "price": 8.1,
          "changedAt": "2026-04-27T15:54:20.677Z",
          "bookmakerOutcomeId": "06e5fd12-ed5e-5453-995e-816c7d422051"
        }
      ]
    },
    {
      "marketId": "10146",
      "bookmakerMarketId": "b7a16d65-ff6d-501e-ad87-51bc536f1704",
      "outcomes": [
        {
          "outcomeId": "10148",
          "playerKey": "0",
          "playerName": null,
          "price": 1.06,
          "changedAt": "2026-04-26T22:44:18.354Z",
          "bookmakerOutcomeId": "9f5c13e2-32c7-52cc-84d7-b3cd89d96980"
        },
        {
          "outcomeId": "10147",
          "playerKey": "0",
          "playerName": null,
          "price": 11,
          "changedAt": "2026-04-26T22:44:18.354Z",
          "bookmakerOutcomeId": "5d580996-69d1-5b2d-af0a-ded14246c98c"
        },
        {
          "outcomeId": "10146",
          "playerKey": "0",
          "playerName": null,
          "price": 20,
          "changedAt": "2026-04-26T22:44:18.354Z",
          "bookmakerOutcomeId": "913f2574-793e-5419-afc3-45b156cce1ce"
        }
      ]
    },
    {
      "marketId": "10149",
      "bookmakerMarketId": "3ca68fb3-c923-5a9c-aba2-9baf5cc6ecec",
      "outcomes": [
        {
          "outcomeId": "10151",
          "playerKey": "0",
          "playerName": null,
          "price": 1.009,
          "changedAt": "2026-04-27T15:54:20.677Z",
          "bookmakerOutcomeId": "5b263101-fca3-5615-94ea-4c90fc6975b2"
        },
        {
          "outcomeId": "10150",
          "playerKey": "0",
          "playerName": null,
          "price": 24,
          "changedAt": "2026-04-27T15:54:20.677Z",
          "bookmakerOutcomeId": "4e578816-ffc3-54de-83d4-e9f9f4db829e"
        },
        {
          "outcomeId": "10149",
          "playerKey": "0",
          "playerName": null,
          "price": 50,
          "changedAt": "2026-04-26T22:44:18.354Z",
          "bookmakerOutcomeId": "474aaeee-fe8d-51c7-a376-eb80aedfe527"
        }
      ]
    },
    {
      "marketId": "10208",
      "bookmakerMarketId": "1ac648af-24cf-541c-bfd2-cfb5575e10be",
      "outcomes": [
        {
          "outcomeId": "10209",
          "playerKey": "0",
          "playerName": null,
          "price": 2.12,
          "changedAt": "2026-04-27T15:54:20.677Z",
          "bookmakerOutcomeId": "c5a8f523-720d-585e-b300-ad919b636a8a"
        },
        {
          "outcomeId": "10208",
          "playerKey": "0",
          "playerName": null,
          "price": 2.7,
          "changedAt": "2026-04-27T15:54:20.677Z",
          "bookmakerOutcomeId": "2beb1f35-d5ff-5db1-86df-ba64b78bfc85"
        },
        {
          "outcomeId": "10210",
          "playerKey": "0",
          "playerName": null,
          "price": 4,
          "changedAt": "2026-04-27T15:54:20.677Z",
          "bookmakerOutcomeId": "260e2103-2477-57cb-854b-698cd880b432"
        }
      ]
    },
    {
      "marketId": "10211",
      "bookmakerMarketId": "7d550928-a38c-58e5-b85b-dd6440d3a731",
      "outcomes": [
        {
          "outcomeId": "10212",
          "playerKey": "0",
          "playerName": null,
          "price": 2.45,
          "changedAt": "2026-04-27T15:54:20.677Z",
          "bookmakerOutcomeId": "3be90909-3a16-5059-a924-6fd2b423a53a"
        },
        {
          "outcomeId": "10211",
          "playerKey": "0",
          "playerName": null,
          "price": 2.47,
          "changedAt": "2026-04-27T15:54:20.677Z",
          "bookmakerOutcomeId": "d785bbbd-01ec-5d85-992f-b9804355b995"
        },
        {
          "outcomeId": "10213",
          "playerKey": "0",
          "playerName": null,
          "price": 3.6,
          "changedAt": "2026-04-27T15:54:20.677Z",
          "bookmakerOutcomeId": "40329a9a-8ea7-5861-ac9b-8417f1eac424"
        }
      ]
    },
    {
      "marketId": "10224",
      "bookmakerMarketId": "41dcff78-c01b-56a6-9603-7db9a79614ea",
      "outcomes": [
        {
          "outcomeId": "10224",
          "playerKey": "0",
          "playerName": null,
          "price": 1.23,
          "changedAt": "2026-04-26T22:44:18.354Z",
          "bookmakerOutcomeId": "b24e7583-f657-52d5-b645-3fae83f3b7d8"
        },
        {
          "outcomeId": "10225",
          "playerKey": "0",
          "playerName": null,
          "price": 3.85,
          "changedAt": "2026-04-26T22:44:18.354Z",
          "bookmakerOutcomeId": "05da9205-9709-5932-91c0-8f3a37a36ee0"
        }
      ]
    },
    {
      "marketId": "10226",
      "bookmakerMarketId": "b27b6f75-0d94-5cc4-8967-29ca74881aa6",
      "outcomes": [
        {
          "outcomeId": "10227",
          "playerKey": "0",
          "playerName": null,
          "price": 1.67,
          "changedAt": "2026-04-26T22:44:18.354Z",
          "bookmakerOutcomeId": "ef420654-29ee-597d-ac9f-f4b8d27b0519"
        },
        {
          "outcomeId": "10226",
          "playerKey": "0",
          "playerName": null,
          "price": 2.12,
          "changedAt": "2026-04-26T22:44:18.354Z",
          "bookmakerOutcomeId": "b6a955da-2aac-5540-b163-b85cad17be1e"
        }
      ]
    },
    {
      "marketId": "10228",
      "bookmakerMarketId": "4c73bc30-5117-5da5-b263-9046c518d61e",
      "outcomes": [
        {
          "outcomeId": "10229",
          "playerKey": "0",
          "playerName": null,
          "price": 1.17,
          "changedAt": "2026-04-26T22:44:18.354Z",
          "bookmakerOutcomeId": "5c243769-d5c7-55e9-94b7-5b43faf8ee8e"
        },
        {
          "outcomeId": "10228",
          "playerKey": "0",
          "playerName": null,
          "price": 4.6,
          "changedAt": "2026-04-26T22:44:18.354Z",
          "bookmakerOutcomeId": "7433028f-ae14-5e38-abed-8e3a0b05b2e1"
        }
      ]
    },
    {
      "marketId": "10230",
      "bookmakerMarketId": "fde0ef83-ba04-5c9f-a5f1-fdb7be44bb03",
      "outcomes": [
        {
          "outcomeId": "10231",
          "playerKey": "0",
          "playerName": null,
          "price": 1.03,
          "changedAt": "2026-04-26T22:44:18.354Z",
          "bookmakerOutcomeId": "db342ed3-a6c0-58df-918d-61267f69279e"
        },
        {
          "outcomeId": "10230",
          "playerKey": "0",
          "playerName": null,
          "price": 11,
          "changedAt": "2026-04-26T22:44:18.354Z",
          "bookmakerOutcomeId": "84072a7c-fffa-591c-92f4-8ed6906d5b16"
        }
      ]
    },
    {
      "marketId": "10232",
      "bookmakerMarketId": "605394cf-57f9-5c3b-b31f-5a4e7897c03f",
      "outcomes": [
        {
          "outcomeId": "10233",
          "playerKey": "0",
          "playerName": null,
          "price": 1.004,
          "changedAt": "2026-04-26T22:44:18.354Z",
          "bookmakerOutcomeId": "81e765ac-5f11-5e98-86fa-3b6ba7706033"
        },
        {
          "outcomeId": "10232",
          "playerKey": "0",
          "playerName": null,
          "price": 28,
          "changedAt": "2026-04-26T22:44:18.354Z",
          "bookmakerOutcomeId": "715bb35a-edeb-584e-b058-56738420ee98"
        }
      ]
    },
    {
      "marketId": "10240",
      "bookmakerMarketId": "6f62ed6a-4a4c-5f62-9418-aac9fe367f38",
      "outcomes": [
        {
          "outcomeId": "10240",
          "playerKey": "0",
          "playerName": null,
          "price": 1.44,
          "changedAt": "2026-04-27T15:54:20.677Z",
          "bookmakerOutcomeId": "c8854020-8795-5320-80db-4aac3f66a43a"
        },
        {
          "outcomeId": "10241",
          "playerKey": "0",
          "playerName": null,
          "price": 2.67,
          "changedAt": "2026-04-27T15:54:20.677Z",
          "bookmakerOutcomeId": "413ca11f-f673-5eb5-8928-c380babbf74b"
        }
      ]
    },
    {
      "marketId": "10242",
      "bookmakerMarketId": "65a68fc8-8c66-5ae6-856a-6b91ca7245ff",
      "outcomes": [
        {
          "outcomeId": "10243",
          "playerKey": "0",
          "playerName": null,
          "price": 1.35,
          "changedAt": "2026-04-27T15:54:20.677Z",
          "bookmakerOutcomeId": "3644ba52-8736-5da6-8d7a-a0df7b4c1587"
        },
        {
          "outcomeId": "10242",
          "playerKey": "0",
          "playerName": null,
          "price": 3.05,
          "changedAt": "2026-04-27T15:54:20.677Z",
          "bookmakerOutcomeId": "25e0b154-2f42-5710-92b9-99a367e7a53e"
        }
      ]
    },
    {
      "marketId": "10244",
      "bookmakerMarketId": "37f0610b-0afb-5799-bf40-b33fceea0d99",
      "outcomes": [
        {
          "outcomeId": "10245",
          "playerKey": "0",
          "playerName": null,
          "price": 1.06,
          "changedAt": "2026-04-27T15:54:20.677Z",
          "bookmakerOutcomeId": "c74c6362-969c-5735-b55c-999bb545306f"
        },
        {
          "outcomeId": "10244",
          "playerKey": "0",
          "playerName": null,
          "price": 7.9,
          "changedAt": "2026-04-27T15:54:20.677Z",
          "bookmakerOutcomeId": "370e18ea-ed5b-564e-9668-6cc723fbcced"
        }
      ]
    },
    {
      "marketId": "10246",
      "bookmakerMarketId": "373ae673-59d9-5e42-bef9-9339c051710d",
      "outcomes": [
        {
          "outcomeId": "10247",
          "playerKey": "0",
          "playerName": null,
          "price": 1.006,
          "changedAt": "2026-04-27T15:54:20.677Z",
          "bookmakerOutcomeId": "11aeec03-c36e-5b55-b743-31002a035520"
        },
        {
          "outcomeId": "10246",
          "playerKey": "0",
          "playerName": null,
          "price": 22,
          "changedAt": "2026-04-27T15:54:20.677Z",
          "bookmakerOutcomeId": "8383c2d5-e9fb-53b7-ba42-fa02cd45374f"
        }
      ]
    },
    {
      "marketId": "10248",
      "bookmakerMarketId": "393cf3c0-f018-57d5-a82b-3eee5ddb2ef2",
      "outcomes": [
        {
          "outcomeId": "10248",
          "playerKey": "0",
          "playerName": null,
          "price": 65,
          "changedAt": "2026-04-27T15:54:20.677Z",
          "bookmakerOutcomeId": "d2a0794a-acd0-534f-b126-d6af1427e96b"
        }
      ]
    },
    {
      "marketId": "10256",
      "bookmakerMarketId": "c8527c9a-ba26-5538-b590-87c5e5fd9526",
      "outcomes": [
        {
          "outcomeId": "10256",
          "playerKey": "0",
          "playerName": null,
          "price": 1.43,
          "changedAt": "2026-04-27T15:54:20.677Z",
          "bookmakerOutcomeId": "79354fab-677e-5b7f-a6b3-f87d4ade6ec7"
        },
        {
          "outcomeId": "10257",
          "playerKey": "0",
          "playerName": null,
          "price": 2.77,
          "changedAt": "2026-04-27T15:54:20.677Z",
          "bookmakerOutcomeId": "ea92330f-8cc6-50e0-af4a-0bdb7c1f6542"
        }
      ]
    },
    {
      "marketId": "10258",
      "bookmakerMarketId": "4c4301a6-c8fa-549c-af6b-5fcbfc1d4df9",
      "outcomes": [
        {
          "outcomeId": "10259",
          "playerKey": "0",
          "playerName": null,
          "price": 1.39,
          "changedAt": "2026-04-27T15:54:20.677Z",
          "bookmakerOutcomeId": "71c26c79-652b-5ef2-b9a5-a2deadcc653c"
        },
        {
          "outcomeId": "10258",
          "playerKey": "0",
          "playerName": null,
          "price": 2.92,
          "changedAt": "2026-04-27T15:54:20.677Z",
          "bookmakerOutcomeId": "e1f72dfd-400f-5041-b86d-cf75668e03b0"
        }
      ]
    },
    {
      "marketId": "10260",
      "bookmakerMarketId": "69f7605a-0e5d-5d77-9c10-5c323a4d1ef0",
      "outcomes": [
        {
          "outcomeId": "10261",
          "playerKey": "0",
          "playerName": null,
          "price": 1.08,
          "changedAt": "2026-04-27T15:54:20.677Z",
          "bookmakerOutcomeId": "efaac007-ba7c-5369-8747-f8da37dc13ad"
        },
        {
          "outcomeId": "10260",
          "playerKey": "0",
          "playerName": null,
          "price": 7.4,
          "changedAt": "2026-04-27T15:54:20.677Z",
          "bookmakerOutcomeId": "599b34a3-09a9-521d-8d83-ed0d69985415"
        }
      ]
    },
    {
      "marketId": "10262",
      "bookmakerMarketId": "7efcf654-2915-56d9-9ca2-6502d2720659",
      "outcomes": [
        {
          "outcomeId": "10263",
          "playerKey": "0",
          "playerName": null,
          "price": 1.01,
          "changedAt": "2026-04-27T15:54:20.677Z",
          "bookmakerOutcomeId": "aa85d9e2-ea7a-5721-abe9-355b04f1cf97"
        },
        {
          "outcomeId": "10262",
          "playerKey": "0",
          "playerName": null,
          "price": 21,
          "changedAt": "2026-04-27T15:54:20.677Z",
          "bookmakerOutcomeId": "555beeed-550a-5d98-9550-e5682d27498e"
        }
      ]
    },
    {
      "marketId": "10264",
      "bookmakerMarketId": "0b9cd689-7f35-5af0-9fa8-3f0982ab1254",
      "outcomes": [
        {
          "outcomeId": "10264",
          "playerKey": "0",
          "playerName": null,
          "price": 50,
          "changedAt": "2026-04-27T15:54:20.677Z",
          "bookmakerOutcomeId": "de728f8b-8b89-5e06-ad1c-76637d8d50d1"
        }
      ]
    },
    {
      "marketId": "10284",
      "bookmakerMarketId": "2b7d60b7-6655-591e-8b20-f24b655e52ce",
      "outcomes": [
        {
          "outcomeId": "10284",
          "playerKey": "0",
          "playerName": null,
          "price": 1.23,
          "changedAt": "2026-04-26T22:44:18.354Z",
          "bookmakerOutcomeId": "cb97c3ad-0653-581a-a186-9c6b3a818fc3"
        },
        {
          "outcomeId": "10285",
          "playerKey": "0",
          "playerName": null,
          "price": 3.85,
          "changedAt": "2026-04-26T22:44:18.354Z",
          "bookmakerOutcomeId": "c61311a0-a971-505e-ada4-12c87c6d5944"
        }
      ]
    },
    {
      "marketId": "10286",
      "bookmakerMarketId": "f2c3ed19-9960-5f6f-8a1b-0f9526b8d2fa",
      "outcomes": [
        {
          "outcomeId": "10286",
          "playerKey": "0",
          "playerName": null,
          "price": 1.44,
          "changedAt": "2026-04-27T15:54:20.677Z",
          "bookmakerOutcomeId": "f5a27e94-94cb-5206-b5e7-ded403b8dae0"
        },
        {
          "outcomeId": "10287",
          "playerKey": "0",
          "playerName": null,
          "price": 2.67,
          "changedAt": "2026-04-27T15:54:20.677Z",
          "bookmakerOutcomeId": "c3854c6d-24b8-50ac-b989-8b4af7f98cdf"
        }
      ]
    },
    {
      "marketId": "10288",
      "bookmakerMarketId": "e09e2778-1565-5c1a-ab45-c1f027edfd13",
      "outcomes": [
        {
          "outcomeId": "10289",
          "playerKey": "0",
          "playerName": null,
          "price": 1.78,
          "changedAt": "2026-04-27T15:54:20.677Z",
          "bookmakerOutcomeId": "fc92b5fa-4e65-5ba3-b96a-70e31946f047"
        },
        {
          "outcomeId": "10288",
          "playerKey": "0",
          "playerName": null,
          "price": 1.92,
          "changedAt": "2026-04-27T15:54:20.677Z",
          "bookmakerOutcomeId": "9e97ad4d-aab0-53be-a990-d2e75d3c3b97"
        }
      ]
    },
    {
      "marketId": "10290",
      "bookmakerMarketId": "3f6ae121-578c-55ea-8198-061f55cb8668",
      "outcomes": [
        {
          "outcomeId": "10291",
          "playerKey": "0",
          "playerName": null,
          "price": 1.51,
          "changedAt": "2026-04-27T15:54:20.677Z",
          "bookmakerOutcomeId": "a4d74842-a8ae-58e1-ac61-096e57df6810"
        },
        {
          "outcomeId": "10290",
          "playerKey": "0",
          "playerName": null,
          "price": 2.4,
          "changedAt": "2026-04-27T15:54:20.677Z",
          "bookmakerOutcomeId": "48954ec6-6a01-5249-b482-f4a9514436b6"
        }
      ]
    },
    {
      "marketId": "10292",
      "bookmakerMarketId": "d6490f8e-c637-5d80-b371-3346d52ac06c",
      "outcomes": [
        {
          "outcomeId": "10292",
          "playerKey": "0",
          "playerName": null,
          "price": 1.66,
          "changedAt": "2026-04-27T15:54:20.677Z",
          "bookmakerOutcomeId": "fd07b128-a64b-5d4a-ae8c-30592bd50756"
        },
        {
          "outcomeId": "10293",
          "playerKey": "0",
          "playerName": null,
          "price": 2.1,
          "changedAt": "2026-04-27T15:54:20.677Z",
          "bookmakerOutcomeId": "6aaa1541-504d-56f0-8fdd-f93e1038262b"
        }
      ]
    },
    {
      "marketId": "10294",
      "bookmakerMarketId": "7b5482ef-260e-5223-8e77-18acbaef726d",
      "outcomes": [
        {
          "outcomeId": "10295",
          "playerKey": "0",
          "playerName": null,
          "price": 1.7,
          "changedAt": "2026-04-27T15:54:20.677Z",
          "bookmakerOutcomeId": "f9b60083-0913-5830-9a58-5a1509250768"
        },
        {
          "outcomeId": "10294",
          "playerKey": "0",
          "playerName": null,
          "price": 2.02,
          "changedAt": "2026-04-27T15:54:20.677Z",
          "bookmakerOutcomeId": "e155c7a0-a939-52b8-987c-b4e5c7acd5e6"
        }
      ]
    },
    {
      "marketId": "10300",
      "bookmakerMarketId": "6208f766-9776-5cde-adbc-e5f0b23884ce",
      "outcomes": [
        {
          "outcomeId": "10301",
          "playerKey": "0",
          "playerName": null,
          "price": 1.17,
          "changedAt": "2026-04-27T15:54:20.677Z",
          "bookmakerOutcomeId": "3416d419-e5b5-5807-a1be-f3d78dcf2250"
        },
        {
          "outcomeId": "10300",
          "playerKey": "0",
          "playerName": null,
          "price": 4.6,
          "changedAt": "2026-04-27T15:54:20.677Z",
          "bookmakerOutcomeId": "7d0f830b-3488-5084-bda7-479ca5079737"
        }
      ]
    },
    {
      "marketId": "10302",
      "bookmakerMarketId": "dd24b850-cf62-5ce9-a6d0-3f9b20481409",
      "outcomes": [
        {
          "outcomeId": "10303",
          "playerKey": "0",
          "playerName": null,
          "price": 1.28,
          "changedAt": "2026-04-27T15:54:20.677Z",
          "bookmakerOutcomeId": "957e559a-abf5-57bf-8c10-2d88b18a8925"
        },
        {
          "outcomeId": "10302",
          "playerKey": "0",
          "playerName": null,
          "price": 3.45,
          "changedAt": "2026-04-27T15:54:20.677Z",
          "bookmakerOutcomeId": "fba379a0-ef76-5a17-8c9d-f0159c1fb1a3"
        }
      ]
    }
  ]
}